playlist_summarizer_core/__init__.py
playlist_summarizer_core/fetcher.py
playlist_summarizer_core/summarizer.py
playlist_summarizer_core-0.1.0.dist-info/WHEEL
playlist_summarizer_core-0.1.0.dist-info/METADATA
playlist_summarizer_core-0.1.0.dist-info/RECORD
