Metadata-Version: 2.3
Name: playlist-summarizer-core
Version: 0.1.0
Summary: Core logic for YouTube playlist transcript fetching and AI-powered summarization
Keywords: youtube,playlist,transcript,summarizer,ai,ollama,llm
Author: Anthony Kovach
Author-email: Anthony Kovach <aj@ajxd2.dev>
Classifier: Development Status :: 4 - Beta
Classifier: Intended Audience :: Developers
Classifier: License :: OSI Approved :: MIT License
Classifier: Programming Language :: Python :: 3
Classifier: Programming Language :: Python :: 3.14
Classifier: Topic :: Multimedia :: Video
Classifier: Topic :: Text Processing :: Markup
Classifier: Topic :: Utilities
Requires-Dist: ollama>=0.6.1
Requires-Dist: python-dotenv>=1.2.1
Requires-Dist: youtube-transcript-api>=1.2.3
Requires-Dist: yt-dlp>=2025.12.8
Requires-Python: >=3.14
